[
  {
    "trade_date": "2025,10,01,00,00,00,000000",
    "ticker": "AMBQ",
    "open": 29.8500003815,
    "high": 30.2001991272,
    "low": 28.9200000763,
    "close": 29.8700008392,
    "volume": 189452.0,
    "wedge_status": "none"
  },
  {
    "trade_date": "2025,10,02,00,00,00,000000",
    "ticker": "AMBQ",
    "open": 29.8500003815,
    "high": 30.125,
    "low": 28.6100006104,
    "close": 29.6800003052,
    "volume": 381636.0,
    "wedge_status": "none"
  },
  {
    "trade_date": "2025,10,03,00,00,00,000000",
    "ticker": "AMBQ",
    "open": 29.6599998474,
    "high": 30.3799991608,
    "low": 29.3299999237,
    "close": 29.8299999237,
    "volume": 174800.0,
    "wedge_status": "none"
  },
  {
    "trade_date": "2025,10,06,00,00,00,000000",
    "ticker": "AMBQ",
    "open": 30.3999996185,
    "high": 31.9200000763,
    "low": 30.0949993134,
    "close": 31.2199993134,
    "volume": 141745.0,
    "wedge_status": "none"
  },
  {
    "trade_date": "2025,10,07,00,00,00,000000",
    "ticker": "AMBQ",
    "open": 31.5,
    "high": 32.6599006653,
    "low": 31.6350002289,
    "close": 32.0999984741,
    "volume": 178232.0,
    "wedge_status": "none"
  },
  {
    "trade_date": "2025,10,08,00,00,00,000000",
    "ticker": "AMBQ",
    "open": 32.5600013733,
    "high": 34.8224983215,
    "low": 32.3800010681,
    "close": 33.8300018311,
    "volume": 176670.0,
    "wedge_status": "none"
  },
  {
    "trade_date": "2025,10,09,00,00,00,000000",
    "ticker": "AMBQ",
    "open": 34.0,
    "high": 34.0800018311,
    "low": 31.7450008392,
    "close": 32.2900009155,
    "volume": 94878.0,
    "wedge_status": "none"
  },
  {
    "trade_date": "2025,10,10,00,00,00,000000",
    "ticker": "AMBQ",
    "open": 32.1899986267,
    "high": 32.8699989319,
    "low": 30.7700004578,
    "close": 30.7700004578,
    "volume": 125500.0,
    "wedge_status": "none"
  },
  {
    "trade_date": "2025,10,13,00,00,00,000000",
    "ticker": "AMBQ",
    "open": 31.6399993896,
    "high": 32.2445983887,
    "low": 31.3999996185,
    "close": 32.0800018311,
    "volume": 69455.0,
    "wedge_status": "none"
  },
  {
    "trade_date": "2025,10,14,00,00,00,000000",
    "ticker": "AMBQ",
    "open": 31.8400001526,
    "high": 32.4000015259,
    "low": 30.5554008484,
    "close": 32.0400009155,
    "volume": 69541.0,
    "wedge_status": "none"
  },
  {
    "trade_date": "2025,10,15,00,00,00,000000",
    "ticker": "AMBQ",
    "open": 32.4799995422,
    "high": 33.2750015259,
    "low": 31.5699996948,
    "close": 31.5699996948,
    "volume": 97172.0,
    "wedge_status": "none"
  },
  {
    "trade_date": "2025,10,16,00,00,00,000000",
    "ticker": "AMBQ",
    "open": 32.0099983215,
    "high": 32.0050010681,
    "low": 29.2399997711,
    "close": 29.4200000763,
    "volume": 84332.0,
    "wedge_status": "none"
  },
  {
    "trade_date": "2025,10,17,00,00,00,000000",
    "ticker": "AMBQ",
    "open": 29.4200000763,
    "high": 30.6399993896,
    "low": 29.2900009155,
    "close": 30.3600006104,
    "volume": 122400.0,
    "wedge_status": "none"
  },
  {
    "trade_date": "2025,10,20,00,00,00,000000",
    "ticker": "AMBQ",
    "open": 30.7900009155,
    "high": 32.5400009155,
    "low": 30.7486000061,
    "close": 31.7800006866,
    "volume": 69186.0,
    "wedge_status": "pop"
  },
  {
    "trade_date": "2025,10,21,00,00,00,000000",
    "ticker": "AMBQ",
    "open": 32.25,
    "high": 32.25,
    "low": 31.2800006866,
    "close": 31.9099998474,
    "volume": 47453.0,
    "wedge_status": "none"
  },
  {
    "trade_date": "2025,10,22,00,00,00,000000",
    "ticker": "AMBQ",
    "open": 31.7399997711,
    "high": 31.5849990845,
    "low": 29.4020004272,
    "close": 29.6299991608,
    "volume": 185067.0,
    "wedge_status": "drop"
  },
  {
    "trade_date": "2025,10,23,00,00,00,000000",
    "ticker": "AMBQ",
    "open": 29.7199993134,
    "high": 30.4130001068,
    "low": 29.6595001221,
    "close": 30.3600006104,
    "volume": 55533.0,
    "wedge_status": "none"
  },
  {
    "trade_date": "2025,10,24,00,00,00,000000",
    "ticker": "AMBQ",
    "open": 30.6800003052,
    "high": 31.1749992371,
    "low": 30.5090007782,
    "close": 31.0900001526,
    "volume": 61829.0,
    "wedge_status": "none"
  },
  {
    "trade_date": "2025,10,27,00,00,00,000000",
    "ticker": "AMBQ",
    "open": 31.4400005341,
    "high": 31.5799999237,
    "low": 29.9899997711,
    "close": 30.4500007629,
    "volume": 67304.0,
    "wedge_status": "none"
  },
  {
    "trade_date": "2025,10,28,00,00,00,000000",
    "ticker": "AMBQ",
    "open": 29.8899993896,
    "high": 30.2919998169,
    "low": 29.5100002289,
    "close": 29.6200008392,
    "volume": 76100.0,
    "wedge_status": "none"
  },
  {
    "trade_date": "2025,10,29,00,00,00,000000",
    "ticker": "AMBQ",
    "open": 29.9400005341,
    "high": 30.8799991608,
    "low": 29.6700000763,
    "close": 30.4099998474,
    "volume": 85960.0,
    "wedge_status": "none"
  },
  {
    "trade_date": "2025,10,30,00,00,00,000000",
    "ticker": "AMBQ",
    "open": 30.1800003052,
    "high": 30.625,
    "low": 29.5599994659,
    "close": 29.7199993134,
    "volume": 60290.0,
    "wedge_status": "none"
  },
  {
    "trade_date": "2025,10,31,00,00,00,000000",
    "ticker": "AMBQ",
    "open": 30.1499996185,
    "high": 30.8600006104,
    "low": 29.875,
    "close": 30.5599994659,
    "volume": 81800.0,
    "wedge_status": "none"
  },
  {
    "trade_date": "2025,11,03,00,00,00,000000",
    "ticker": "AMBQ",
    "open": 30.7800006866,
    "high": 30.6100006104,
    "low": 29.0100002289,
    "close": 29.2900009155,
    "volume": 71657.0,
    "wedge_status": "none"
  },
  {
    "trade_date": "2025,11,04,00,00,00,000000",
    "ticker": "AMBQ",
    "open": 29.0,
    "high": 29.0,
    "low": 27.2600002289,
    "close": 27.5400009155,
    "volume": 121871.0,
    "wedge_status": "none"
  }
]