[
  {
    "trade_date": "2025,08,27,00,00,00,000000",
    "ticker": "RAL",
    "open": 41.5299987793,
    "high": 42.7400016785,
    "low": 41.4700012207,
    "close": 42.3300018311,
    "volume": 856489.0,
    "wedge_status": "none"
  },
  {
    "trade_date": "2025,08,28,00,00,00,000000",
    "ticker": "RAL",
    "open": 42.3800010681,
    "high": 42.9799995422,
    "low": 41.6199989319,
    "close": 42.6899986267,
    "volume": 759642.0,
    "wedge_status": "none"
  },
  {
    "trade_date": "2025,08,29,00,00,00,000000",
    "ticker": "RAL",
    "open": 42.3699989319,
    "high": 43.0900001526,
    "low": 41.7799987793,
    "close": 41.8100013733,
    "volume": 706000.0,
    "wedge_status": "none"
  },
  {
    "trade_date": "2025,09,02,00,00,00,000000",
    "ticker": "RAL",
    "open": 42.1399993896,
    "high": 42.8300018311,
    "low": 41.0,
    "close": 42.5900001526,
    "volume": 1369764.0,
    "wedge_status": "none"
  },
  {
    "trade_date": "2025,09,03,00,00,00,000000",
    "ticker": "RAL",
    "open": 42.6300010681,
    "high": 43.2799987793,
    "low": 41.8499984741,
    "close": 42.2700004578,
    "volume": 780867.0,
    "wedge_status": "none"
  },
  {
    "trade_date": "2025,09,04,00,00,00,000000",
    "ticker": "RAL",
    "open": 42.2799987793,
    "high": 43.0999984741,
    "low": 42.0600013733,
    "close": 42.7900009155,
    "volume": 1288471.0,
    "wedge_status": "none"
  },
  {
    "trade_date": "2025,09,05,00,00,00,000000",
    "ticker": "RAL",
    "open": 43.6100006104,
    "high": 44.4000015259,
    "low": 42.8100013733,
    "close": 43.2799987793,
    "volume": 858010.0,
    "wedge_status": "none"
  },
  {
    "trade_date": "2025,09,08,00,00,00,000000",
    "ticker": "RAL",
    "open": 43.2200012207,
    "high": 43.7200012207,
    "low": 42.0,
    "close": 42.3300018311,
    "volume": 957644.0,
    "wedge_status": "none"
  },
  {
    "trade_date": "2025,09,09,00,00,00,000000",
    "ticker": "RAL",
    "open": 42.2099990845,
    "high": 42.4500007629,
    "low": 41.3499984741,
    "close": 42.2599983215,
    "volume": 985129.0,
    "wedge_status": "none"
  },
  {
    "trade_date": "2025,09,10,00,00,00,000000",
    "ticker": "RAL",
    "open": 42.9700012207,
    "high": 43.3499984741,
    "low": 41.7799987793,
    "close": 41.9500007629,
    "volume": 1078512.0,
    "wedge_status": "none"
  },
  {
    "trade_date": "2025,09,11,00,00,00,000000",
    "ticker": "RAL",
    "open": 41.8899993896,
    "high": 43.1100006104,
    "low": 41.4199981689,
    "close": 42.9199981689,
    "volume": 1463745.0,
    "wedge_status": "none"
  },
  {
    "trade_date": "2025,09,12,00,00,00,000000",
    "ticker": "RAL",
    "open": 42.7200012207,
    "high": 42.7599983215,
    "low": 41.3100013733,
    "close": 41.3199996948,
    "volume": 990701.0,
    "wedge_status": "none"
  },
  {
    "trade_date": "2025,09,15,00,00,00,000000",
    "ticker": "RAL",
    "open": 41.3199996948,
    "high": 42.2550010681,
    "low": 41.0600013733,
    "close": 41.3199996948,
    "volume": 861834.0,
    "wedge_status": "none"
  },
  {
    "trade_date": "2025,09,16,00,00,00,000000",
    "ticker": "RAL",
    "open": 41.2000007629,
    "high": 41.8499984741,
    "low": 40.7000007629,
    "close": 41.8300018311,
    "volume": 908905.0,
    "wedge_status": "none"
  },
  {
    "trade_date": "2025,09,17,00,00,00,000000",
    "ticker": "RAL",
    "open": 41.8899993896,
    "high": 42.8149986267,
    "low": 41.5901985168,
    "close": 41.8899993896,
    "volume": 1120837.0,
    "wedge_status": "none"
  },
  {
    "trade_date": "2025,09,18,00,00,00,000000",
    "ticker": "RAL",
    "open": 42.5,
    "high": 44.1500015259,
    "low": 42.5099983215,
    "close": 43.7599983215,
    "volume": 1818447.0,
    "wedge_status": "none"
  },
  {
    "trade_date": "2025,09,19,00,00,00,000000",
    "ticker": "RAL",
    "open": 44.3100013733,
    "high": 44.3100013733,
    "low": 42.7999992371,
    "close": 43.4199981689,
    "volume": 2486734.0,
    "wedge_status": "none"
  },
  {
    "trade_date": "2025,09,22,00,00,00,000000",
    "ticker": "RAL",
    "open": 43.0,
    "high": 44.5099983215,
    "low": 43.0200004578,
    "close": 44.3800010681,
    "volume": 1008663.0,
    "wedge_status": "none"
  },
  {
    "trade_date": "2025,09,23,00,00,00,000000",
    "ticker": "RAL",
    "open": 44.5999984741,
    "high": 44.9599990845,
    "low": 43.8549995422,
    "close": 44.0600013733,
    "volume": 844595.0,
    "wedge_status": "none"
  },
  {
    "trade_date": "2025,09,24,00,00,00,000000",
    "ticker": "RAL",
    "open": 44.3400001526,
    "high": 44.625,
    "low": 43.2700004578,
    "close": 43.8899993896,
    "volume": 771540.0,
    "wedge_status": "none"
  },
  {
    "trade_date": "2025,09,25,00,00,00,000000",
    "ticker": "RAL",
    "open": 43.0699996948,
    "high": 43.2999992371,
    "low": 42.0600013733,
    "close": 42.7000007629,
    "volume": 892611.0,
    "wedge_status": "drop"
  },
  {
    "trade_date": "2025,09,26,00,00,00,000000",
    "ticker": "RAL",
    "open": 42.5,
    "high": 43.3801002502,
    "low": 42.25,
    "close": 43.1500015259,
    "volume": 648968.0,
    "wedge_status": "none"
  },
  {
    "trade_date": "2025,09,29,00,00,00,000000",
    "ticker": "RAL",
    "open": 43.5600013733,
    "high": 43.7200012207,
    "low": 42.4799995422,
    "close": 42.8199996948,
    "volume": 801796.0,
    "wedge_status": "drop"
  },
  {
    "trade_date": "2025,09,30,00,00,00,000000",
    "ticker": "RAL",
    "open": 43.0,
    "high": 43.7700004578,
    "low": 42.3499984741,
    "close": 43.7299995422,
    "volume": 1037569.0,
    "wedge_status": "pop"
  },
  {
    "trade_date": "2025,10,01,00,00,00,000000",
    "ticker": "RAL",
    "open": 43.1800003052,
    "high": 44.4300003052,
    "low": 42.7599983215,
    "close": 44.1599998474,
    "volume": 1042309.0,
    "wedge_status": "none"
  },
  {
    "trade_date": "2025,10,02,00,00,00,000000",
    "ticker": "RAL",
    "open": 44.7000007629,
    "high": 45.7799987793,
    "low": 43.754901886,
    "close": 44.2200012207,
    "volume": 867965.0,
    "wedge_status": "none"
  },
  {
    "trade_date": "2025,10,03,00,00,00,000000",
    "ticker": "RAL",
    "open": 44.3100013733,
    "high": 45.0275001526,
    "low": 44.25,
    "close": 44.2999992371,
    "volume": 746784.0,
    "wedge_status": "none"
  },
  {
    "trade_date": "2025,10,06,00,00,00,000000",
    "ticker": "RAL",
    "open": 44.9500007629,
    "high": 45.1624984741,
    "low": 43.8899993896,
    "close": 43.9799995422,
    "volume": 685721.0,
    "wedge_status": "none"
  },
  {
    "trade_date": "2025,10,07,00,00,00,000000",
    "ticker": "RAL",
    "open": 44.0800018311,
    "high": 44.2599983215,
    "low": 43.2700004578,
    "close": 43.8300018311,
    "volume": 495035.0,
    "wedge_status": "none"
  },
  {
    "trade_date": "2025,10,08,00,00,00,000000",
    "ticker": "RAL",
    "open": 44.0299987793,
    "high": 44.7099990845,
    "low": 43.4099998474,
    "close": 44.5400009155,
    "volume": 587233.0,
    "wedge_status": "none"
  },
  {
    "trade_date": "2025,10,09,00,00,00,000000",
    "ticker": "RAL",
    "open": 44.2900009155,
    "high": 44.3199996948,
    "low": 43.0900001526,
    "close": 43.2200012207,
    "volume": 478055.0,
    "wedge_status": "drop"
  },
  {
    "trade_date": "2025,10,10,00,00,00,000000",
    "ticker": "RAL",
    "open": 43.6500015259,
    "high": 43.8300018311,
    "low": 41.4000015259,
    "close": 41.4199981689,
    "volume": 846100.0,
    "wedge_status": "none"
  },
  {
    "trade_date": "2025,10,13,00,00,00,000000",
    "ticker": "RAL",
    "open": 42.1500015259,
    "high": 42.5299987793,
    "low": 41.6850013733,
    "close": 41.8400001526,
    "volume": 877015.0,
    "wedge_status": "none"
  },
  {
    "trade_date": "2025,10,14,00,00,00,000000",
    "ticker": "RAL",
    "open": 41.5099983215,
    "high": 42.7299995422,
    "low": 41.2700004578,
    "close": 42.4700012207,
    "volume": 968256.0,
    "wedge_status": "none"
  },
  {
    "trade_date": "2025,10,15,00,00,00,000000",
    "ticker": "RAL",
    "open": 42.8499984741,
    "high": 43.2799987793,
    "low": 42.7550010681,
    "close": 43.1899986267,
    "volume": 1074586.0,
    "wedge_status": "none"
  },
  {
    "trade_date": "2025,10,16,00,00,00,000000",
    "ticker": "RAL",
    "open": 43.4300003052,
    "high": 43.7599983215,
    "low": 42.9049987793,
    "close": 43.0400009155,
    "volume": 929268.0,
    "wedge_status": "none"
  },
  {
    "trade_date": "2025,10,17,00,00,00,000000",
    "ticker": "RAL",
    "open": 42.9599990845,
    "high": 43.5,
    "low": 41.6049995422,
    "close": 42.3499984741,
    "volume": 1176600.0,
    "wedge_status": "drop"
  },
  {
    "trade_date": "2025,10,20,00,00,00,000000",
    "ticker": "RAL",
    "open": 42.4000015259,
    "high": 43.1199989319,
    "low": 42.2700004578,
    "close": 42.5400009155,
    "volume": 824269.0,
    "wedge_status": "none"
  },
  {
    "trade_date": "2025,10,21,00,00,00,000000",
    "ticker": "RAL",
    "open": 42.9399986267,
    "high": 43.7000007629,
    "low": 42.8450012207,
    "close": 43.3899993896,
    "volume": 922354.0,
    "wedge_status": "none"
  },
  {
    "trade_date": "2025,10,22,00,00,00,000000",
    "ticker": "RAL",
    "open": 43.1899986267,
    "high": 43.25,
    "low": 42.0125007629,
    "close": 42.4199981689,
    "volume": 712466.0,
    "wedge_status": "none"
  },
  {
    "trade_date": "2025,10,23,00,00,00,000000",
    "ticker": "RAL",
    "open": 42.2200012207,
    "high": 43.4500007629,
    "low": 42.2200012207,
    "close": 43.4500007629,
    "volume": 709418.0,
    "wedge_status": "none"
  },
  {
    "trade_date": "2025,10,24,00,00,00,000000",
    "ticker": "RAL",
    "open": 43.5400009155,
    "high": 44.2550010681,
    "low": 43.1100006104,
    "close": 43.4099998474,
    "volume": 1182695.0,
    "wedge_status": "none"
  },
  {
    "trade_date": "2025,10,27,00,00,00,000000",
    "ticker": "RAL",
    "open": 44.0699996948,
    "high": 44.2299995422,
    "low": 43.1549987793,
    "close": 43.5499992371,
    "volume": 710201.0,
    "wedge_status": "none"
  },
  {
    "trade_date": "2025,10,28,00,00,00,000000",
    "ticker": "RAL",
    "open": 43.2400016785,
    "high": 43.6599998474,
    "low": 42.5800018311,
    "close": 42.9599990845,
    "volume": 1248000.0,
    "wedge_status": "none"
  },
  {
    "trade_date": "2025,10,29,00,00,00,000000",
    "ticker": "RAL",
    "open": 43.3699989319,
    "high": 44.9799995422,
    "low": 43.0849990845,
    "close": 43.5800018311,
    "volume": 1383374.0,
    "wedge_status": "none"
  },
  {
    "trade_date": "2025,10,30,00,00,00,000000",
    "ticker": "RAL",
    "open": 43.3499984741,
    "high": 44.2799987793,
    "low": 43.2200012207,
    "close": 43.6199989319,
    "volume": 1189840.0,
    "wedge_status": "none"
  },
  {
    "trade_date": "2025,10,31,00,00,00,000000",
    "ticker": "RAL",
    "open": 43.2000007629,
    "high": 44.1549987793,
    "low": 43.1399993896,
    "close": 43.9199981689,
    "volume": 1338500.0,
    "wedge_status": "none"
  },
  {
    "trade_date": "2025,11,03,00,00,00,000000",
    "ticker": "RAL",
    "open": 43.9099998474,
    "high": 44.3100013733,
    "low": 42.8499984741,
    "close": 44.2799987793,
    "volume": 627012.0,
    "wedge_status": "none"
  },
  {
    "trade_date": "2025,11,04,00,00,00,000000",
    "ticker": "RAL",
    "open": 43.7299995422,
    "high": 44.0900001526,
    "low": 43.0999984741,
    "close": 43.1800003052,
    "volume": 639192.0,
    "wedge_status": "none"
  },
  {
    "trade_date": "2025,11,05,00,00,00,000000",
    "ticker": "RAL",
    "open": 43.0800018311,
    "high": 44.9500007629,
    "low": 43.0349998474,
    "close": 44.4000015259,
    "volume": 1378466.0,
    "wedge_status": "none"
  },
  {
    "trade_date": "2025,11,06,00,00,00,000000",
    "ticker": "RAL",
    "open": 43.0299987793,
    "high": 47.7599983215,
    "low": 42.6300010681,
    "close": 46.8600006104,
    "volume": 2407084.0,
    "wedge_status": "none"
  },
  {
    "trade_date": "2025,11,07,00,00,00,000000",
    "ticker": "RAL",
    "open": 47.0900001526,
    "high": 47.4550018311,
    "low": 45.7000007629,
    "close": 46.6500015259,
    "volume": 1962235.0,
    "wedge_status": "none"
  },
  {
    "trade_date": "2025,11,10,00,00,00,000000",
    "ticker": "RAL",
    "open": 47.0099983215,
    "high": 47.2200012207,
    "low": 45.8400001526,
    "close": 45.9199981689,
    "volume": 845585.0,
    "wedge_status": "none"
  },
  {
    "trade_date": "2025,11,11,00,00,00,000000",
    "ticker": "RAL",
    "open": 46.6100006104,
    "high": 47.1949996948,
    "low": 46.2400016785,
    "close": 46.75,
    "volume": 1147769.0,
    "wedge_status": "none"
  },
  {
    "trade_date": "2025,11,12,00,00,00,000000",
    "ticker": "RAL",
    "open": 46.6800003052,
    "high": 48.8300018311,
    "low": 46.75,
    "close": 47.7799987793,
    "volume": 2566315.0,
    "wedge_status": "none"
  },
  {
    "trade_date": "2025,11,13,00,00,00,000000",
    "ticker": "RAL",
    "open": 47.6500015259,
    "high": 48.0,
    "low": 46.3493995667,
    "close": 47.3199996948,
    "volume": 1402901.0,
    "wedge_status": "none"
  },
  {
    "trade_date": "2025,11,14,00,00,00,000000",
    "ticker": "RAL",
    "open": 47.0099983215,
    "high": 47.9199981689,
    "low": 46.5,
    "close": 47.4599990845,
    "volume": 1094508.0,
    "wedge_status": "none"
  },
  {
    "trade_date": "2025,11,17,00,00,00,000000",
    "ticker": "RAL",
    "open": 47.2000007629,
    "high": 47.7400016785,
    "low": 45.9799995422,
    "close": 46.4799995422,
    "volume": 1517014.0,
    "wedge_status": "none"
  },
  {
    "trade_date": "2025,11,18,00,00,00,000000",
    "ticker": "RAL",
    "open": 46.1100006104,
    "high": 47.0699996948,
    "low": 44.7999992371,
    "close": 45.7599983215,
    "volume": 1158202.0,
    "wedge_status": "none"
  },
  {
    "trade_date": "2025,11,19,00,00,00,000000",
    "ticker": "RAL",
    "open": 45.5699996948,
    "high": 46.4249992371,
    "low": 45.3499984741,
    "close": 46.0600013733,
    "volume": 1162966.0,
    "wedge_status": "none"
  },
  {
    "trade_date": "2025,11,20,00,00,00,000000",
    "ticker": "RAL",
    "open": 46.4599990845,
    "high": 47.6100006104,
    "low": 44.3250007629,
    "close": 44.5699996948,
    "volume": 1530917.0,
    "wedge_status": "drop"
  },
  {
    "trade_date": "2025,11,21,00,00,00,000000",
    "ticker": "RAL",
    "open": 44.4300003052,
    "high": 46.2999992371,
    "low": 44.1300010681,
    "close": 45.9700012207,
    "volume": 1204987.0,
    "wedge_status": "none"
  },
  {
    "trade_date": "2025,11,24,00,00,00,000000",
    "ticker": "RAL",
    "open": 45.9700012207,
    "high": 46.9000015259,
    "low": 45.6699981689,
    "close": 46.8600006104,
    "volume": 733056.0,
    "wedge_status": "none"
  },
  {
    "trade_date": "2025,11,25,00,00,00,000000",
    "ticker": "RAL",
    "open": 47.2999992371,
    "high": 48.875,
    "low": 47.3100013733,
    "close": 48.0999984741,
    "volume": 1158270.0,
    "wedge_status": "none"
  },
  {
    "trade_date": "2025,11,26,00,00,00,000000",
    "ticker": "RAL",
    "open": 48.3699989319,
    "high": 49.7999992371,
    "low": 48.1399993896,
    "close": 48.7799987793,
    "volume": 989887.0,
    "wedge_status": "none"
  },
  {
    "trade_date": "2025,11,28,00,00,00,000000",
    "ticker": "RAL",
    "open": 49.0600013733,
    "high": 49.9900016785,
    "low": 48.3849983215,
    "close": 49.3699989319,
    "volume": 861090.0,
    "wedge_status": "none"
  },
  {
    "trade_date": "2025,12,01,00,00,00,000000",
    "ticker": "RAL",
    "open": 48.9599990845,
    "high": 49.2949981689,
    "low": 48.5499992371,
    "close": 48.7799987793,
    "volume": 1023752.0,
    "wedge_status": "none"
  },
  {
    "trade_date": "2025,12,02,00,00,00,000000",
    "ticker": "RAL",
    "open": 48.8300018311,
    "high": 49.125,
    "low": 48.2350006104,
    "close": 48.7400016785,
    "volume": 1346775.0,
    "wedge_status": "none"
  },
  {
    "trade_date": "2025,12,03,00,00,00,000000",
    "ticker": "RAL",
    "open": 48.5,
    "high": 50.6500015259,
    "low": 48.1199989319,
    "close": 50.3800010681,
    "volume": 1310597.0,
    "wedge_status": "none"
  },
  {
    "trade_date": "2025,12,04,00,00,00,000000",
    "ticker": "RAL",
    "open": 50.2900009155,
    "high": 51.7700004578,
    "low": 50.0449981689,
    "close": 51.6300010681,
    "volume": 1019480.0,
    "wedge_status": "none"
  },
  {
    "trade_date": "2025,12,05,00,00,00,000000",
    "ticker": "RAL",
    "open": 51.2400016785,
    "high": 51.3499984741,
    "low": 50.1800003052,
    "close": 51.0999984741,
    "volume": 2193862.0,
    "wedge_status": "none"
  },
  {
    "trade_date": "2025,12,08,00,00,00,000000",
    "ticker": "RAL",
    "open": 52.3699989319,
    "high": 52.4350013733,
    "low": 50.9199981689,
    "close": 51.3300018311,
    "volume": 1107369.0,
    "wedge_status": "none"
  },
  {
    "trade_date": "2025,12,09,00,00,00,000000",
    "ticker": "RAL",
    "open": 50.9900016785,
    "high": 52.3899993896,
    "low": 50.6699981689,
    "close": 50.9500007629,
    "volume": 976372.0,
    "wedge_status": "none"
  },
  {
    "trade_date": "2025,12,10,00,00,00,000000",
    "ticker": "RAL",
    "open": 50.7700004578,
    "high": 51.75,
    "low": 50.2299995422,
    "close": 51.4000015259,
    "volume": 1410462.0,
    "wedge_status": "none"
  },
  {
    "trade_date": "2025,12,11,00,00,00,000000",
    "ticker": "RAL",
    "open": 51.3600006104,
    "high": 52.4249992371,
    "low": 50.8600006104,
    "close": 52.2200012207,
    "volume": 994732.0,
    "wedge_status": "none"
  },
  {
    "trade_date": "2025,12,12,00,00,00,000000",
    "ticker": "RAL",
    "open": 52.8899993896,
    "high": 52.6500015259,
    "low": 50.5600013733,
    "close": 50.9599990845,
    "volume": 902863.0,
    "wedge_status": "none"
  },
  {
    "trade_date": "2025,12,15,00,00,00,000000",
    "ticker": "RAL",
    "open": 51.2299995422,
    "high": 51.6949996948,
    "low": 50.5699996948,
    "close": 50.7799987793,
    "volume": 780241.0,
    "wedge_status": "none"
  },
  {
    "trade_date": "2025,12,16,00,00,00,000000",
    "ticker": "RAL",
    "open": 50.8499984741,
    "high": 51.4500007629,
    "low": 50.3100013733,
    "close": 50.5,
    "volume": 992100.0,
    "wedge_status": "none"
  },
  {
    "trade_date": "2025,12,17,00,00,00,000000",
    "ticker": "RAL",
    "open": 50.4700012207,
    "high": 50.9799995422,
    "low": 49.5699996948,
    "close": 49.9199981689,
    "volume": 865336.0,
    "wedge_status": "none"
  },
  {
    "trade_date": "2025,12,18,00,00,00,000000",
    "ticker": "RAL",
    "open": 50.4000015259,
    "high": 50.9099998474,
    "low": 49.5999984741,
    "close": 50.9099998474,
    "volume": 1191188.0,
    "wedge_status": "none"
  },
  {
    "trade_date": "2025,12,19,00,00,00,000000",
    "ticker": "RAL",
    "open": 50.5099983215,
    "high": 52.3499984741,
    "low": 51.0,
    "close": 52.2700004578,
    "volume": 4247156.0,
    "wedge_status": "none"
  },
  {
    "trade_date": "2025,12,22,00,00,00,000000",
    "ticker": "RAL",
    "open": 52.4900016785,
    "high": 52.5400009155,
    "low": 51.5499992371,
    "close": 51.7200012207,
    "volume": 838678.0,
    "wedge_status": "none"
  },
  {
    "trade_date": "2025,12,23,00,00,00,000000",
    "ticker": "RAL",
    "open": 51.8199996948,
    "high": 52.3349990845,
    "low": 50.4199981689,
    "close": 51.5999984741,
    "volume": 1006530.0,
    "wedge_status": "none"
  },
  {
    "trade_date": "2025,12,24,00,00,00,000000",
    "ticker": "RAL",
    "open": 51.8199996948,
    "high": 52.0900001526,
    "low": 51.3199996948,
    "close": 51.6500015259,
    "volume": 486004.0,
    "wedge_status": "none"
  },
  {
    "trade_date": "2025,12,26,00,00,00,000000",
    "ticker": "RAL",
    "open": 51.5600013733,
    "high": 51.9700012207,
    "low": 51.0999984741,
    "close": 51.4900016785,
    "volume": 888935.0,
    "wedge_status": "none"
  },
  {
    "trade_date": "2025,12,29,00,00,00,000000",
    "ticker": "RAL",
    "open": 51.2299995422,
    "high": 51.4599990845,
    "low": 50.7999992371,
    "close": 51.25,
    "volume": 710299.0,
    "wedge_status": "none"
  },
  {
    "trade_date": "2025,12,30,00,00,00,000000",
    "ticker": "RAL",
    "open": 51.1699981689,
    "high": 51.3100013733,
    "low": 50.6699981689,
    "close": 51.2200012207,
    "volume": 644655.0,
    "wedge_status": "none"
  },
  {
    "trade_date": "2025,12,31,00,00,00,000000",
    "ticker": "RAL",
    "open": 51.2299995422,
    "high": 51.6399993896,
    "low": 50.7537994385,
    "close": 50.9099998474,
    "volume": 622130.0,
    "wedge_status": "none"
  },
  {
    "trade_date": "2026,01,02,00,00,00,000000",
    "ticker": "RAL",
    "open": 51.4399986267,
    "high": 51.3400001526,
    "low": 50.3499984741,
    "close": 51.2200012207,
    "volume": 752426.0,
    "wedge_status": "none"
  },
  {
    "trade_date": "2026,01,05,00,00,00,000000",
    "ticker": "RAL",
    "open": 50.9399986267,
    "high": 52.5424995422,
    "low": 50.6640014648,
    "close": 51.6300010681,
    "volume": 1042535.0,
    "wedge_status": "none"
  },
  {
    "trade_date": "2026,01,06,00,00,00,000000",
    "ticker": "RAL",
    "open": 50.9399986267,
    "high": 52.2599983215,
    "low": 51.1800003052,
    "close": 52.0,
    "volume": 902950.0,
    "wedge_status": "none"
  },
  {
    "trade_date": "2026,01,07,00,00,00,000000",
    "ticker": "RAL",
    "open": 52.4700012207,
    "high": 52.9799995422,
    "low": 51.4199981689,
    "close": 52.1500015259,
    "volume": 552089.0,
    "wedge_status": "none"
  }
]