[
  {
    "trade_date": "2026,02,19,00,00,00,000000",
    "ticker": "VSNT",
    "open": 30.0,
    "high": 30.4500007629,
    "low": 29.5300006866,
    "close": 30.0400009155,
    "volume": 2615036.0,
    "wedge_status": "none"
  },
  {
    "trade_date": "2026,02,20,00,00,00,000000",
    "ticker": "VSNT",
    "open": 30.0599994659,
    "high": 30.4699993134,
    "low": 29.7700004578,
    "close": 30.0300006866,
    "volume": 2014900.0,
    "wedge_status": "none"
  },
  {
    "trade_date": "2026,02,23,00,00,00,000000",
    "ticker": "VSNT",
    "open": 29.9200000763,
    "high": 29.9599990845,
    "low": 29.2000007629,
    "close": 29.6000003815,
    "volume": 1898947.0,
    "wedge_status": "none"
  },
  {
    "trade_date": "2026,02,24,00,00,00,000000",
    "ticker": "VSNT",
    "open": 29.7299995422,
    "high": 30.3099994659,
    "low": 29.4699993134,
    "close": 29.8500003815,
    "volume": 3124024.0,
    "wedge_status": "none"
  },
  {
    "trade_date": "2026,02,25,00,00,00,000000",
    "ticker": "VSNT",
    "open": 29.8500003815,
    "high": 31.2299995422,
    "low": 29.8099994659,
    "close": 31.0,
    "volume": 2410770.0,
    "wedge_status": "none"
  },
  {
    "trade_date": "2026,02,26,00,00,00,000000",
    "ticker": "VSNT",
    "open": 30.8099994659,
    "high": 32.5099983215,
    "low": 30.8099994659,
    "close": 32.4799995422,
    "volume": 3028303.0,
    "wedge_status": "none"
  },
  {
    "trade_date": "2026,02,27,00,00,00,000000",
    "ticker": "VSNT",
    "open": 32.5800018311,
    "high": 34.1300010681,
    "low": 32.3499984741,
    "close": 33.3199996948,
    "volume": 4957157.0,
    "wedge_status": "none"
  },
  {
    "trade_date": "2026,03,02,00,00,00,000000",
    "ticker": "VSNT",
    "open": 32.6399993896,
    "high": 33.4599990845,
    "low": 32.2000007629,
    "close": 32.7400016785,
    "volume": 2128122.0,
    "wedge_status": "none"
  },
  {
    "trade_date": "2026,03,03,00,00,00,000000",
    "ticker": "VSNT",
    "open": 33.1399993896,
    "high": 34.5499992371,
    "low": 32.0950012207,
    "close": 34.0099983215,
    "volume": 5273752.0,
    "wedge_status": "none"
  },
  {
    "trade_date": "2026,03,04,00,00,00,000000",
    "ticker": "VSNT",
    "open": 34.2799987793,
    "high": 36.25,
    "low": 34.2799987793,
    "close": 36.0200004578,
    "volume": 5264558.0,
    "wedge_status": "none"
  },
  {
    "trade_date": "2026,03,05,00,00,00,000000",
    "ticker": "VSNT",
    "open": 36.0200004578,
    "high": 36.9500007629,
    "low": 35.7900009155,
    "close": 36.7700004578,
    "volume": 3703754.0,
    "wedge_status": "none"
  },
  {
    "trade_date": "2026,03,06,00,00,00,000000",
    "ticker": "VSNT",
    "open": 36.5299987793,
    "high": 37.5550003052,
    "low": 36.25,
    "close": 36.7000007629,
    "volume": 2680394.0,
    "wedge_status": "none"
  },
  {
    "trade_date": "2026,03,09,00,00,00,000000",
    "ticker": "VSNT",
    "open": 36.1199989319,
    "high": 37.0200004578,
    "low": 35.9000015259,
    "close": 36.5400009155,
    "volume": 2394490.0,
    "wedge_status": "none"
  },
  {
    "trade_date": "2026,03,10,00,00,00,000000",
    "ticker": "VSNT",
    "open": 37.0,
    "high": 37.5099983215,
    "low": 36.4300003052,
    "close": 36.6100006104,
    "volume": 2429132.0,
    "wedge_status": "none"
  },
  {
    "trade_date": "2026,03,11,00,00,00,000000",
    "ticker": "VSNT",
    "open": 36.8300018311,
    "high": 38.3899993896,
    "low": 36.8300018311,
    "close": 38.2999992371,
    "volume": 3504300.0,
    "wedge_status": "none"
  },
  {
    "trade_date": "2026,03,12,00,00,00,000000",
    "ticker": "VSNT",
    "open": 38.1500015259,
    "high": 38.6500015259,
    "low": 37.4599990845,
    "close": 37.6500015259,
    "volume": 2913684.0,
    "wedge_status": "none"
  },
  {
    "trade_date": "2026,03,13,00,00,00,000000",
    "ticker": "VSNT",
    "open": 37.5,
    "high": 38.2633018494,
    "low": 37.1899986267,
    "close": 37.5499992371,
    "volume": 2899794.0,
    "wedge_status": "none"
  },
  {
    "trade_date": "2026,03,16,00,00,00,000000",
    "ticker": "VSNT",
    "open": 37.5400009155,
    "high": 38.2949981689,
    "low": 37.0,
    "close": 38.0,
    "volume": 2550600.0,
    "wedge_status": "none"
  },
  {
    "trade_date": "2026,03,17,00,00,00,000000",
    "ticker": "VSNT",
    "open": 38.0699996948,
    "high": 38.3800010681,
    "low": 37.5800018311,
    "close": 37.9500007629,
    "volume": 1714300.0,
    "wedge_status": "none"
  },
  {
    "trade_date": "2026,03,18,00,00,00,000000",
    "ticker": "VSNT",
    "open": 37.75,
    "high": 37.7900009155,
    "low": 35.0999984741,
    "close": 35.9099998474,
    "volume": 3170200.0,
    "wedge_status": "none"
  },
  {
    "trade_date": "2026,03,19,00,00,00,000000",
    "ticker": "VSNT",
    "open": 35.5900001526,
    "high": 35.7900009155,
    "low": 34.6399993896,
    "close": 35.5,
    "volume": 2400508.0,
    "wedge_status": "none"
  },
  {
    "trade_date": "2026,03,20,00,00,00,000000",
    "ticker": "VSNT",
    "open": 35.7099990845,
    "high": 36.2900009155,
    "low": 34.9900016785,
    "close": 36.2299995422,
    "volume": 5387436.0,
    "wedge_status": "none"
  },
  {
    "trade_date": "2026,03,23,00,00,00,000000",
    "ticker": "VSNT",
    "open": 35.6300010681,
    "high": 37.3300018311,
    "low": 35.5499992371,
    "close": 36.5999984741,
    "volume": 2489624.0,
    "wedge_status": "none"
  },
  {
    "trade_date": "2026,03,24,00,00,00,000000",
    "ticker": "VSNT",
    "open": 36.4900016785,
    "high": 37.1399993896,
    "low": 35.4700012207,
    "close": 36.1300010681,
    "volume": 1981853.0,
    "wedge_status": "none"
  },
  {
    "trade_date": "2026,03,25,00,00,00,000000",
    "ticker": "VSNT",
    "open": 36.2599983215,
    "high": 36.7799987793,
    "low": 35.8899993896,
    "close": 36.5,
    "volume": 1669873.0,
    "wedge_status": "none"
  },
  {
    "trade_date": "2026,03,26,00,00,00,000000",
    "ticker": "VSNT",
    "open": 36.25,
    "high": 36.4799995422,
    "low": 35.8300018311,
    "close": 36.0900001526,
    "volume": 1640716.0,
    "wedge_status": "none"
  },
  {
    "trade_date": "2026,03,27,00,00,00,000000",
    "ticker": "VSNT",
    "open": 35.7999992371,
    "high": 36.2000007629,
    "low": 35.1100006104,
    "close": 35.4300003052,
    "volume": 1836220.0,
    "wedge_status": "drop"
  },
  {
    "trade_date": "2026,03,30,00,00,00,000000",
    "ticker": "VSNT",
    "open": 35.0999984741,
    "high": 36.1850013733,
    "low": 35.0999984741,
    "close": 35.5900001526,
    "volume": 2158812.0,
    "wedge_status": "none"
  },
  {
    "trade_date": "2026,03,31,00,00,00,000000",
    "ticker": "VSNT",
    "open": 35.9799995422,
    "high": 37.5999984741,
    "low": 35.9500007629,
    "close": 37.0200004578,
    "volume": 2662187.0,
    "wedge_status": "none"
  },
  {
    "trade_date": "2026,04,01,00,00,00,000000",
    "ticker": "VSNT",
    "open": 36.6199989319,
    "high": 37.4500007629,
    "low": 36.3400001526,
    "close": 37.1800003052,
    "volume": 1897624.0,
    "wedge_status": "none"
  },
  {
    "trade_date": "2026,04,02,00,00,00,000000",
    "ticker": "VSNT",
    "open": 37.0299987793,
    "high": 37.5649986267,
    "low": 36.5999984741,
    "close": 37.4300003052,
    "volume": 1589934.0,
    "wedge_status": "none"
  },
  {
    "trade_date": "2026,04,06,00,00,00,000000",
    "ticker": "VSNT",
    "open": 37.5800018311,
    "high": 38.2299995422,
    "low": 37.4099998474,
    "close": 37.8300018311,
    "volume": 1498549.0,
    "wedge_status": "none"
  },
  {
    "trade_date": "2026,04,07,00,00,00,000000",
    "ticker": "VSNT",
    "open": 37.8300018311,
    "high": 38.2400016785,
    "low": 37.4099998474,
    "close": 38.0299987793,
    "volume": 1238363.0,
    "wedge_status": "none"
  },
  {
    "trade_date": "2026,04,08,00,00,00,000000",
    "ticker": "VSNT",
    "open": 38.4599990845,
    "high": 38.9000015259,
    "low": 38.400100708,
    "close": 38.5299987793,
    "volume": 1579215.0,
    "wedge_status": "none"
  },
  {
    "trade_date": "2026,04,09,00,00,00,000000",
    "ticker": "VSNT",
    "open": 38.25,
    "high": 38.8800010681,
    "low": 37.5499992371,
    "close": 38.7999992371,
    "volume": 1491025.0,
    "wedge_status": "none"
  },
  {
    "trade_date": "2026,04,10,00,00,00,000000",
    "ticker": "VSNT",
    "open": 38.8100013733,
    "high": 40.061000824,
    "low": 38.5029983521,
    "close": 39.75,
    "volume": 1637877.0,
    "wedge_status": "none"
  },
  {
    "trade_date": "2026,04,13,00,00,00,000000",
    "ticker": "VSNT",
    "open": 39.7299995422,
    "high": 40.8499984741,
    "low": 39.5999984741,
    "close": 40.8300018311,
    "volume": 1789650.0,
    "wedge_status": "none"
  },
  {
    "trade_date": "2026,04,14,00,00,00,000000",
    "ticker": "VSNT",
    "open": 40.9900016785,
    "high": 41.3699989319,
    "low": 40.4099998474,
    "close": 41.1500015259,
    "volume": 2362219.0,
    "wedge_status": "none"
  },
  {
    "trade_date": "2026,04,15,00,00,00,000000",
    "ticker": "VSNT",
    "open": 41.1800003052,
    "high": 41.5550003052,
    "low": 40.7649993896,
    "close": 41.0,
    "volume": 2255693.0,
    "wedge_status": "none"
  },
  {
    "trade_date": "2026,04,16,00,00,00,000000",
    "ticker": "VSNT",
    "open": 41.4799995422,
    "high": 42.1698989868,
    "low": 40.9099998474,
    "close": 41.0800018311,
    "volume": 2124993.0,
    "wedge_status": "none"
  },
  {
    "trade_date": "2026,04,17,00,00,00,000000",
    "ticker": "VSNT",
    "open": 41.1850013733,
    "high": 41.1850013733,
    "low": 40.1450004578,
    "close": 40.8600006104,
    "volume": 2707642.0,
    "wedge_status": "none"
  },
  {
    "trade_date": "2026,04,20,00,00,00,000000",
    "ticker": "VSNT",
    "open": 40.7000007629,
    "high": 41.6850013733,
    "low": 40.4500007629,
    "close": 40.7999992371,
    "volume": 1849457.0,
    "wedge_status": "none"
  },
  {
    "trade_date": "2026,04,21,00,00,00,000000",
    "ticker": "VSNT",
    "open": 40.7999992371,
    "high": 41.0349998474,
    "low": 39.6199989319,
    "close": 39.6500015259,
    "volume": 1663547.0,
    "wedge_status": "none"
  },
  {
    "trade_date": "2026,04,22,00,00,00,000000",
    "ticker": "VSNT",
    "open": 40.2000007629,
    "high": 40.3450012207,
    "low": 39.6300010681,
    "close": 40.3199996948,
    "volume": 2172073.0,
    "wedge_status": "none"
  },
  {
    "trade_date": "2026,04,23,00,00,00,000000",
    "ticker": "VSNT",
    "open": 40.2099990845,
    "high": 41.0,
    "low": 39.9599990845,
    "close": 40.4900016785,
    "volume": 1797202.0,
    "wedge_status": "none"
  },
  {
    "trade_date": "2026,04,24,00,00,00,000000",
    "ticker": "VSNT",
    "open": 40.3651008606,
    "high": 40.6800003052,
    "low": 38.3600006104,
    "close": 38.7400016785,
    "volume": 2212098.0,
    "wedge_status": "none"
  },
  {
    "trade_date": "2026,04,27,00,00,00,000000",
    "ticker": "VSNT",
    "open": 38.7400016785,
    "high": 39.9000015259,
    "low": 38.7200012207,
    "close": 39.9000015259,
    "volume": 1831453.0,
    "wedge_status": "none"
  },
  {
    "trade_date": "2026,04,28,00,00,00,000000",
    "ticker": "VSNT",
    "open": 40.0600013733,
    "high": 40.1899986267,
    "low": 39.1500015259,
    "close": 39.1599998474,
    "volume": 1508492.0,
    "wedge_status": "none"
  },
  {
    "trade_date": "2026,04,29,00,00,00,000000",
    "ticker": "VSNT",
    "open": 39.0,
    "high": 40.0600013733,
    "low": 38.7750015259,
    "close": 39.6300010681,
    "volume": 1501256.0,
    "wedge_status": "none"
  },
  {
    "trade_date": "2026,04,30,00,00,00,000000",
    "ticker": "VSNT",
    "open": 39.3499984741,
    "high": 40.5849990845,
    "low": 39.3499984741,
    "close": 40.1899986267,
    "volume": 1721849.0,
    "wedge_status": "none"
  },
  {
    "trade_date": "2026,05,01,00,00,00,000000",
    "ticker": "VSNT",
    "open": 40.5999984741,
    "high": 43.0600013733,
    "low": 40.243598938,
    "close": 40.8300018311,
    "volume": 1933174.0,
    "wedge_status": "none"
  },
  {
    "trade_date": "2026,05,04,00,00,00,000000",
    "ticker": "VSNT",
    "open": 40.75,
    "high": 41.7598991394,
    "low": 40.6100006104,
    "close": 41.4000015259,
    "volume": 1345158.0,
    "wedge_status": "none"
  },
  {
    "trade_date": "2026,05,05,00,00,00,000000",
    "ticker": "VSNT",
    "open": 41.6500015259,
    "high": 41.7400016785,
    "low": 40.7400016785,
    "close": 40.8800010681,
    "volume": 1363691.0,
    "wedge_status": "none"
  },
  {
    "trade_date": "2026,05,06,00,00,00,000000",
    "ticker": "VSNT",
    "open": 41.2700004578,
    "high": 41.4900016785,
    "low": 40.7099990845,
    "close": 40.9700012207,
    "volume": 1122823.0,
    "wedge_status": "none"
  },
  {
    "trade_date": "2026,05,07,00,00,00,000000",
    "ticker": "VSNT",
    "open": 40.8800010681,
    "high": 41.2999992371,
    "low": 40.6800003052,
    "close": 40.7799987793,
    "volume": 1494071.0,
    "wedge_status": "none"
  },
  {
    "trade_date": "2026,05,08,00,00,00,000000",
    "ticker": "VSNT",
    "open": 40.3699989319,
    "high": 41.1800994873,
    "low": 40.1199989319,
    "close": 41.1399993896,
    "volume": 1226103.0,
    "wedge_status": "none"
  },
  {
    "trade_date": "2026,05,11,00,00,00,000000",
    "ticker": "VSNT",
    "open": 41.3300018311,
    "high": 41.7900009155,
    "low": 41.2200012207,
    "close": 41.3100013733,
    "volume": 1289703.0,
    "wedge_status": "none"
  },
  {
    "trade_date": "2026,05,12,00,00,00,000000",
    "ticker": "VSNT",
    "open": 41.0,
    "high": 41.2200012207,
    "low": 39.4550018311,
    "close": 40.3699989319,
    "volume": 3073756.0,
    "wedge_status": "none"
  },
  {
    "trade_date": "2026,05,13,00,00,00,000000",
    "ticker": "VSNT",
    "open": 40.3400001526,
    "high": 41.2099990845,
    "low": 39.9900016785,
    "close": 40.4399986267,
    "volume": 2345900.0,
    "wedge_status": "none"
  },
  {
    "trade_date": "2026,05,14,00,00,00,000000",
    "ticker": "VSNT",
    "open": 43.25,
    "high": 45.5800018311,
    "low": 41.3499984741,
    "close": 44.4300003052,
    "volume": 4695063.0,
    "wedge_status": "none"
  },
  {
    "trade_date": "2026,05,15,00,00,00,000000",
    "ticker": "VSNT",
    "open": 43.4900016785,
    "high": 43.7900009155,
    "low": 41.7799987793,
    "close": 42.9799995422,
    "volume": 3250428.0,
    "wedge_status": "none"
  },
  {
    "trade_date": "2026,05,18,00,00,00,000000",
    "ticker": "VSNT",
    "open": 43.1399993896,
    "high": 43.4900016785,
    "low": 42.0999984741,
    "close": 42.2900009155,
    "volume": 1892228.0,
    "wedge_status": "none"
  },
  {
    "trade_date": "2026,05,19,00,00,00,000000",
    "ticker": "VSNT",
    "open": 42.2299995422,
    "high": 42.5800018311,
    "low": 41.9599990845,
    "close": 42.3800010681,
    "volume": 1670210.0,
    "wedge_status": "none"
  },
  {
    "trade_date": "2026,05,20,00,00,00,000000",
    "ticker": "VSNT",
    "open": 42.5200004578,
    "high": 42.9500007629,
    "low": 41.7099990845,
    "close": 41.8800010681,
    "volume": 1413442.0,
    "wedge_status": "none"
  },
  {
    "trade_date": "2026,05,21,00,00,00,000000",
    "ticker": "VSNT",
    "open": 41.7599983215,
    "high": 42.2599983215,
    "low": 41.375,
    "close": 42.1300010681,
    "volume": 1660530.0,
    "wedge_status": "none"
  },
  {
    "trade_date": "2026,05,22,00,00,00,000000",
    "ticker": "VSNT",
    "open": 42.1100006104,
    "high": 43.0499992371,
    "low": 42.0299987793,
    "close": 42.6699981689,
    "volume": 1359290.0,
    "wedge_status": "none"
  },
  {
    "trade_date": "2026,05,26,00,00,00,000000",
    "ticker": "VSNT",
    "open": 42.9000015259,
    "high": 43.3450012207,
    "low": 42.5999984741,
    "close": 42.7000007629,
    "volume": 1613501.0,
    "wedge_status": "none"
  },
  {
    "trade_date": "2026,05,27,00,00,00,000000",
    "ticker": "VSNT",
    "open": 42.6300010681,
    "high": 43.7999992371,
    "low": 42.5999984741,
    "close": 43.4000015259,
    "volume": 1278980.0,
    "wedge_status": "none"
  },
  {
    "trade_date": "2026,05,28,00,00,00,000000",
    "ticker": "VSNT",
    "open": 43.2200012207,
    "high": 43.6949996948,
    "low": 43.0,
    "close": 43.3300018311,
    "volume": 1259798.0,
    "wedge_status": "none"
  },
  {
    "trade_date": "2026,05,29,00,00,00,000000",
    "ticker": "VSNT",
    "open": 42.7999992371,
    "high": 43.1599998474,
    "low": 42.4599990845,
    "close": 43.1399993896,
    "volume": 1687078.0,
    "wedge_status": "none"
  }
]