[
  {
    "trade_date": "2025,07,21,00,00,00,000000",
    "ticker": "AXS",
    "open": 97.4599990845,
    "high": 97.6399993896,
    "low": 96.0999984741,
    "close": 96.0999984741,
    "volume": 381030.0,
    "wedge_status": "none"
  },
  {
    "trade_date": "2025,07,22,00,00,00,000000",
    "ticker": "AXS",
    "open": 96.3099975586,
    "high": 97.7300033569,
    "low": 96.3099975586,
    "close": 96.9899978638,
    "volume": 487487.0,
    "wedge_status": "none"
  },
  {
    "trade_date": "2025,07,23,00,00,00,000000",
    "ticker": "AXS",
    "open": 96.9000015259,
    "high": 97.3899993896,
    "low": 95.9800033569,
    "close": 97.3499984741,
    "volume": 600169.0,
    "wedge_status": "none"
  },
  {
    "trade_date": "2025,07,24,00,00,00,000000",
    "ticker": "AXS",
    "open": 96.5599975586,
    "high": 96.9160003662,
    "low": 95.75,
    "close": 95.9300003052,
    "volume": 446496.0,
    "wedge_status": "none"
  },
  {
    "trade_date": "2025,07,25,00,00,00,000000",
    "ticker": "AXS",
    "open": 96.3600006104,
    "high": 97.3050003052,
    "low": 95.9700012207,
    "close": 96.9800033569,
    "volume": 350077.0,
    "wedge_status": "none"
  },
  {
    "trade_date": "2025,07,28,00,00,00,000000",
    "ticker": "AXS",
    "open": 96.6600036621,
    "high": 96.8399963379,
    "low": 96.0999984741,
    "close": 96.2799987793,
    "volume": 570137.0,
    "wedge_status": "none"
  }
]